{"categories":["lancamentos","sofa","on sale","venda","cadeiras","teste"],"__N_SSG":true,"pageProps":{"product":{"categories":["venda","cadeiras"],"name":"Josh Jones Red Chair","price":"1200","image":"/products/chair8.png","description":"Você não precisa sair para ser resistente. O sofá de couro cru Cigar apresenta uma estrutura robusta de madeira com cantos bloqueados e costuras brutas para aquele visual de Malboro. Este sofá de couro marrom é aconchegante em uma casa de campo, cabana ou condomínio. E o couro (o couro!) fica mais bonito com o uso: marcas sutis de caracteres como picadas de insetos, cicatrizes cicatrizadas e variação de grão refletem uma verdadeira safra. Prepare-se e passe o controle remoto.","brand":"Jason Bourne","currentInventory":17,"id":"f25091b1-ccf2-4236-957a-2809785037ab"}}}